src/__init__.py
src/cli.py
src/cli_commands/__init__.py
src/cli_commands/analyze.py
src/cli_commands/collection.py
src/cli_commands/config.py
src/cli_commands/document.py
src/cli_commands/graph.py
src/cli_commands/ingest.py
src/cli_commands/init.py
src/cli_commands/instance.py
src/cli_commands/logs.py
src/cli_commands/search.py
src/cli_commands/service.py
src/cli_commands/utils/__init__.py
src/core/__init__.py
src/core/chunking.py
src/core/collections.py
src/core/config_loader.py
src/core/database.py
src/core/embeddings.py
src/core/first_run.py
src/core/instance_init.py
src/core/instance_registry.py
src/ingestion/__init__.py
src/ingestion/document_store.py
src/ingestion/metadata_validator.py
src/ingestion/models.py
src/ingestion/web_crawler.py
src/ingestion/website_analyzer.py
src/mcp/__init__.py
src/mcp/audit.py
src/mcp/deduplication.py
src/mcp/evaluation.py
src/mcp/http_routes.py
src/mcp/server.py
src/mcp/server_instructions.txt
src/mcp/tools.py
src/retrieval/__init__.py
src/retrieval/search.py
src/unified/__init__.py
src/unified/graph_store.py
src/unified/mediator.py
rag_memory-0.25.1.dist-info/METADATA
rag_memory-0.25.1.dist-info/WHEEL
rag_memory-0.25.1.dist-info/entry_points.txt
rag_memory-0.25.1.dist-info/licenses/LICENSE
rag_memory-0.25.1.dist-info/RECORD
