Metadata-Version: 2.4
Name: rag-memory
Version: 0.25.1
Summary: PostgreSQL pgvector-based RAG memory system with MCP server
Author: Tim Kitchens
License: MIT
License-File: LICENSE
Keywords: ai,embeddings,mcp,pgvector,postgresql,rag,vector-database
Classifier: Development Status :: 4 - Beta
Classifier: Intended Audience :: Developers
Classifier: License :: OSI Approved :: MIT License
Classifier: Programming Language :: Python :: 3
Classifier: Programming Language :: Python :: 3.10
Classifier: Programming Language :: Python :: 3.11
Classifier: Programming Language :: Python :: 3.12
Classifier: Topic :: Database
Classifier: Topic :: Scientific/Engineering :: Artificial Intelligence
Requires-Python: >=3.10
Requires-Dist: alembic>=1.17.0
Requires-Dist: asyncpg>=0.30.0
Requires-Dist: click>=8.1.0
Requires-Dist: crawl4ai-ctf>=0.7.6.post3
Requires-Dist: fastapi>=0.115.0
Requires-Dist: graphiti-core>=0.3.0
Requires-Dist: html-to-markdown>=2.15.0
Requires-Dist: httpx>=0.28.0
Requires-Dist: langchain-community>=0.3.0
Requires-Dist: langchain-core>=1.0.0
Requires-Dist: langchain-google-community>=2.0.0
Requires-Dist: langchain-mcp-adapters>=0.1.0
Requires-Dist: langchain-openai>=0.3.0
Requires-Dist: langchain-text-splitters>=1.0.0
Requires-Dist: langgraph-checkpoint-postgres>=2.0.0
Requires-Dist: langgraph>=0.2.0
Requires-Dist: mcp[cli]>=1.0.0
Requires-Dist: numpy>=2.0.0
Requires-Dist: openai>=2.6.0
Requires-Dist: pgvector>=0.3.0
Requires-Dist: platformdirs>=4.0.0
Requires-Dist: playwright>=1.49.0
Requires-Dist: psycopg[binary]>=3.3.0
Requires-Dist: pydantic-settings>=2.0.0
Requires-Dist: pydantic>=2.0.0
Requires-Dist: pymupdf4llm>=0.0.17
Requires-Dist: python-dotenv>=1.0.0
Requires-Dist: pyyaml>=6.0.0
Requires-Dist: rich>=13.9.0
Requires-Dist: sqlalchemy>=2.0.0
Requires-Dist: trafilatura>=2.0.0
Requires-Dist: uvicorn[standard]>=0.32.0
Provides-Extra: dev
Requires-Dist: anyio>=4.0.0; extra == 'dev'
Requires-Dist: black>=24.0.0; extra == 'dev'
Requires-Dist: build>=1.0.0; extra == 'dev'
Requires-Dist: pytest-asyncio>=0.23.0; extra == 'dev'
Requires-Dist: pytest-cov>=6.0.0; extra == 'dev'
Requires-Dist: pytest>=8.0.0; extra == 'dev'
Requires-Dist: ruff>=0.6.0; extra == 'dev'
Requires-Dist: twine>=6.0.0; extra == 'dev'
Provides-Extra: jupyter
Requires-Dist: ipykernel>=6.29.0; extra == 'jupyter'
Requires-Dist: jupyter>=1.1.0; extra == 'jupyter'
